{
  "US:QQQ": {
    "return_pct": -1.13,
    "value": null,
    "value_type": "return_pct",
    "status": "traded",
    "source": "sina_us_intraday_regular_http",
    "trade_date": "2026-05-19",
    "quote_time_bj": "2026-05-19 22:40:51",
    "fetched_at_bj": "2026-05-19T22:40:56+08:00",
    "error": ""
  },
  "US:NFLX": {
    "return_pct": 1.26,
    "value": null,
    "value_type": "return_pct",
    "status": "traded",
    "source": "sina_us_intraday_regular_http",
    "trade_date": "2026-05-19",
    "quote_time_bj": "2026-05-19 22:40:51",
    "fetched_at_bj": "2026-05-19T22:40:56+08:00",
    "error": ""
  },
  "US:NVDA": {
    "return_pct": -1.09,
    "value": null,
    "value_type": "return_pct",
    "status": "traded",
    "source": "sina_us_intraday_regular_http",
    "trade_date": "2026-05-19",
    "quote_time_bj": "2026-05-19 22:40:51",
    "fetched_at_bj": "2026-05-19T22:40:56+08:00",
    "error": ""
  },
  "US:AAPL": {
    "return_pct": -0.32,
    "value": null,
    "value_type": "return_pct",
    "status": "traded",
    "source": "sina_us_intraday_regular_http",
    "trade_date": "2026-05-19",
    "quote_time_bj": "2026-05-19 22:40:51",
    "fetched_at_bj": "2026-05-19T22:40:56+08:00",
    "error": ""
  },
  "US:MSFT": {
    "return_pct": 0.25,
    "value": null,
    "value_type": "return_pct",
    "status": "traded",
    "source": "sina_us_intraday_regular_http",
    "trade_date": "2026-05-19",
    "quote_time_bj": "2026-05-19 22:40:51",
    "fetched_at_bj": "2026-05-19T22:40:56+08:00",
    "error": ""
  },
  "US:AVGO": {
    "return_pct": -2.66,
    "value": null,
    "value_type": "return_pct",
    "status": "traded",
    "source": "sina_us_intraday_regular_http",
    "trade_date": "2026-05-19",
    "quote_time_bj": "2026-05-19 22:40:51",
    "fetched_at_bj": "2026-05-19T22:40:56+08:00",
    "error": ""
  },
  "US:TSLA": {
    "return_pct": -3.12,
    "value": null,
    "value_type": "return_pct",
    "status": "traded",
    "source": "sina_us_intraday_regular_http",
    "trade_date": "2026-05-19",
    "quote_time_bj": "2026-05-19 22:40:51",
    "fetched_at_bj": "2026-05-19T22:40:56+08:00",
    "error": ""
  },
  "US:GOOG": {
    "return_pct": -1.37,
    "value": null,
    "value_type": "return_pct",
    "status": "traded",
    "source": "sina_us_intraday_regular_http",
    "trade_date": "2026-05-19",
    "quote_time_bj": "2026-05-19 22:40:56",
    "fetched_at_bj": "2026-05-19T22:40:56+08:00",
    "error": ""
  },
  "US:AMZN": {
    "return_pct": -2.81,
    "value": null,
    "value_type": "return_pct",
    "status": "traded",
    "source": "sina_us_intraday_regular_http",
    "trade_date": "2026-05-19",
    "quote_time_bj": "2026-05-19 22:40:56",
    "fetched_at_bj": "2026-05-19T22:40:56+08:00",
    "error": ""
  },
  "US:META": {
    "return_pct": -0.56,
    "value": null,
    "value_type": "return_pct",
    "status": "traded",
    "source": "sina_us_intraday_regular_http",
    "trade_date": "2026-05-19",
    "quote_time_bj": "2026-05-19 22:40:56",
    "fetched_at_bj": "2026-05-19T22:40:56+08:00",
    "error": ""
  },
  "US:MRVL": {
    "return_pct": -0.73,
    "value": null,
    "value_type": "return_pct",
    "status": "traded",
    "source": "sina_us_intraday_regular_http",
    "trade_date": "2026-05-19",
    "quote_time_bj": "2026-05-19 22:40:56",
    "fetched_at_bj": "2026-05-19T22:40:56+08:00",
    "error": ""
  },
  "US:TSM": {
    "return_pct": -2.1,
    "value": null,
    "value_type": "return_pct",
    "status": "traded",
    "source": "sina_us_intraday_regular_http",
    "trade_date": "2026-05-19",
    "quote_time_bj": "2026-05-19 22:40:56",
    "fetched_at_bj": "2026-05-19T22:40:56+08:00",
    "error": ""
  },
  "US:LITE": {
    "return_pct": -2.88,
    "value": null,
    "value_type": "return_pct",
    "status": "traded",
    "source": "sina_us_intraday_regular_http",
    "trade_date": "2026-05-19",
    "quote_time_bj": "2026-05-19 22:40:56",
    "fetched_at_bj": "2026-05-19T22:40:56+08:00",
    "error": ""
  },
  "CN:300502": {
    "return_pct": -4.57,
    "value": null,
    "value_type": "return_pct",
    "status": "traded",
    "source": "ak_stock_zh_a_hist_pct",
    "trade_date": "2026-05-19",
    "quote_time_bj": "",
    "fetched_at_bj": "2026-05-19T22:40:56+08:00",
    "error": ""
  },
  "US:GLW": {
    "return_pct": -4.16,
    "value": null,
    "value_type": "return_pct",
    "status": "traded",
    "source": "sina_us_intraday_regular_http",
    "trade_date": "2026-05-19",
    "quote_time_bj": "2026-05-19 22:40:56",
    "fetched_at_bj": "2026-05-19T22:40:56+08:00",
    "error": ""
  },
  "US:AXTI": {
    "return_pct": 4.41,
    "value": null,
    "value_type": "return_pct",
    "status": "traded",
    "source": "sina_us_intraday_regular_http",
    "trade_date": "2026-05-19",
    "quote_time_bj": "2026-05-19 22:40:56",
    "fetched_at_bj": "2026-05-19T22:40:56+08:00",
    "error": ""
  },
  "CN:300308": {
    "return_pct": -1.44,
    "value": null,
    "value_type": "return_pct",
    "status": "traded",
    "source": "ak_stock_zh_a_hist_pct",
    "trade_date": "2026-05-19",
    "quote_time_bj": "",
    "fetched_at_bj": "2026-05-19T22:40:56+08:00",
    "error": ""
  },
  "CN:688498": {
    "return_pct": 0.94,
    "value": null,
    "value_type": "return_pct",
    "status": "traded",
    "source": "ak_stock_zh_a_hist_pct",
    "trade_date": "2026-05-19",
    "quote_time_bj": "",
    "fetched_at_bj": "2026-05-19T22:40:56+08:00",
    "error": ""
  },
  "US:TSEM": {
    "return_pct": -2.55,
    "value": null,
    "value_type": "return_pct",
    "status": "traded",
    "source": "sina_us_intraday_regular_http",
    "trade_date": "2026-05-19",
    "quote_time_bj": "2026-05-19 22:40:55",
    "fetched_at_bj": "2026-05-19T22:40:56+08:00",
    "error": ""
  },
  "US:GOOGL": {
    "return_pct": -1.51,
    "value": null,
    "value_type": "return_pct",
    "status": "traded",
    "source": "sina_us_intraday_regular_http",
    "trade_date": "2026-05-19",
    "quote_time_bj": "2026-05-19 22:40:56",
    "fetched_at_bj": "2026-05-19T22:40:56+08:00",
    "error": ""
  },
  "CN:002384": {
    "return_pct": 5.13,
    "value": null,
    "value_type": "return_pct",
    "status": "traded",
    "source": "ak_stock_zh_a_hist_pct",
    "trade_date": "2026-05-19",
    "quote_time_bj": "",
    "fetched_at_bj": "2026-05-19T22:40:56+08:00",
    "error": ""
  },
  "US:MU": {
    "return_pct": -1.42,
    "value": null,
    "value_type": "return_pct",
    "status": "traded",
    "source": "sina_us_intraday_regular_http",
    "trade_date": "2026-05-19",
    "quote_time_bj": "2026-05-19 22:40:56",
    "fetched_at_bj": "2026-05-19T22:40:56+08:00",
    "error": ""
  },
  "US:AMD": {
    "return_pct": -5.19,
    "value": null,
    "value_type": "return_pct",
    "status": "traded",
    "source": "sina_us_intraday_regular_http",
    "trade_date": "2026-05-19",
    "quote_time_bj": "2026-05-19 22:40:56",
    "fetched_at_bj": "2026-05-19T22:40:56+08:00",
    "error": ""
  },
  "US:CIEN": {
    "return_pct": -2.94,
    "value": null,
    "value_type": "return_pct",
    "status": "traded",
    "source": "sina_us_intraday_regular_http",
    "trade_date": "2026-05-19",
    "quote_time_bj": "2026-05-19 22:40:56",
    "fetched_at_bj": "2026-05-19T22:40:56+08:00",
    "error": ""
  },
  "US:COHR": {
    "return_pct": -5.64,
    "value": null,
    "value_type": "return_pct",
    "status": "traded",
    "source": "sina_us_intraday_regular_http",
    "trade_date": "2026-05-19",
    "quote_time_bj": "2026-05-19 22:40:56",
    "fetched_at_bj": "2026-05-19T22:40:56+08:00",
    "error": ""
  },
  "US:VIAV": {
    "return_pct": -4.98,
    "value": null,
    "value_type": "return_pct",
    "status": "traded",
    "source": "sina_us_intraday_regular_http",
    "trade_date": "2026-05-19",
    "quote_time_bj": "2026-05-19 22:40:53",
    "fetched_at_bj": "2026-05-19T22:40:56+08:00",
    "error": ""
  },
  "US:SNDK": {
    "return_pct": -1.71,
    "value": null,
    "value_type": "return_pct",
    "status": "traded",
    "source": "sina_us_intraday_regular_http",
    "trade_date": "2026-05-19",
    "quote_time_bj": "2026-05-19 22:40:56",
    "fetched_at_bj": "2026-05-19T22:40:56+08:00",
    "error": ""
  },
  "US:AEIS": {
    "return_pct": -4.57,
    "value": null,
    "value_type": "return_pct",
    "status": "traded",
    "source": "sina_us_intraday_regular_http",
    "trade_date": "2026-05-19",
    "quote_time_bj": "2026-05-19 22:40:56",
    "fetched_at_bj": "2026-05-19T22:40:56+08:00",
    "error": ""
  },
  "US:TER": {
    "return_pct": -2.43,
    "value": null,
    "value_type": "return_pct",
    "status": "traded",
    "source": "sina_us_intraday_regular_http",
    "trade_date": "2026-05-19",
    "quote_time_bj": "2026-05-19 22:40:56",
    "fetched_at_bj": "2026-05-19T22:40:56+08:00",
    "error": ""
  },
  "US:LRCX": {
    "return_pct": -4.01,
    "value": null,
    "value_type": "return_pct",
    "status": "traded",
    "source": "sina_us_intraday_regular_http",
    "trade_date": "2026-05-19",
    "quote_time_bj": "2026-05-19 22:40:56",
    "fetched_at_bj": "2026-05-19T22:40:56+08:00",
    "error": ""
  },
  "US:MKSI": {
    "return_pct": -4.07,
    "value": null,
    "value_type": "return_pct",
    "status": "traded",
    "source": "sina_us_intraday_regular_http",
    "trade_date": "2026-05-19",
    "quote_time_bj": "2026-05-19 22:40:50",
    "fetched_at_bj": "2026-05-19T22:40:56+08:00",
    "error": ""
  },
  "US:TTMI": {
    "return_pct": -5.09,
    "value": null,
    "value_type": "return_pct",
    "status": "traded",
    "source": "sina_us_intraday_regular_http",
    "trade_date": "2026-05-19",
    "quote_time_bj": "2026-05-19 22:40:55",
    "fetched_at_bj": "2026-05-19T22:40:56+08:00",
    "error": ""
  },
  "US:INTC": {
    "return_pct": -3.7,
    "value": null,
    "value_type": "return_pct",
    "status": "traded",
    "source": "sina_us_intraday_regular_http",
    "trade_date": "2026-05-19",
    "quote_time_bj": "2026-05-19 22:41:01",
    "fetched_at_bj": "2026-05-19T22:40:56+08:00",
    "error": ""
  },
  "US:ASML": {
    "return_pct": -1.55,
    "value": null,
    "value_type": "return_pct",
    "status": "traded",
    "source": "sina_us_intraday_regular_http",
    "trade_date": "2026-05-19",
    "quote_time_bj": "2026-05-19 22:41:01",
    "fetched_at_bj": "2026-05-19T22:40:56+08:00",
    "error": ""
  },
  "HK:02513": {
    "return_pct": -9.41,
    "value": null,
    "value_type": "return_pct",
    "status": "traded",
    "source": "ak_stock_hk_hist_em_pct",
    "trade_date": "2026-05-19",
    "quote_time_bj": "",
    "fetched_at_bj": "2026-05-19T22:40:56+08:00",
    "error": ""
  },
  "US:KLAC": {
    "return_pct": -2.52,
    "value": null,
    "value_type": "return_pct",
    "status": "traded",
    "source": "sina_us_intraday_regular_http",
    "trade_date": "2026-05-19",
    "quote_time_bj": "2026-05-19 22:41:01",
    "fetched_at_bj": "2026-05-19T22:40:56+08:00",
    "error": ""
  },
  "HK:09899": {
    "return_pct": -0.08,
    "value": null,
    "value_type": "return_pct",
    "status": "traded",
    "source": "ak_stock_hk_hist_em_pct",
    "trade_date": "2026-05-19",
    "quote_time_bj": "",
    "fetched_at_bj": "2026-05-19T22:40:56+08:00",
    "error": ""
  },
  "HK:00522": {
    "return_pct": -4.08,
    "value": null,
    "value_type": "return_pct",
    "status": "traded",
    "source": "ak_stock_hk_hist_em_pct",
    "trade_date": "2026-05-19",
    "quote_time_bj": "",
    "fetched_at_bj": "2026-05-19T22:40:56+08:00",
    "error": ""
  },
  "KR:000660": {
    "return_pct": -5.163043478260869,
    "value": null,
    "value_type": "return_pct",
    "status": "traded",
    "source": "pykrx_ohlcv_pct",
    "trade_date": "2026-05-19",
    "quote_time_bj": "",
    "fetched_at_bj": "2026-05-19T22:40:56+08:00",
    "error": ""
  },
  "KR:005930": {
    "return_pct": -1.9572953736654803,
    "value": null,
    "value_type": "return_pct",
    "status": "traded",
    "source": "pykrx_ohlcv_pct",
    "trade_date": "2026-05-19",
    "quote_time_bj": "",
    "fetched_at_bj": "2026-05-19T22:40:56+08:00",
    "error": ""
  },
  "CN:300476": {
    "return_pct": -2.6632004621605976,
    "value": null,
    "value_type": "return_pct",
    "status": "traded",
    "source": "ak_stock_zh_a_daily_sina_qfq_close_calc",
    "trade_date": "2026-05-19",
    "quote_time_bj": "",
    "fetched_at_bj": "2026-05-19T22:40:56+08:00",
    "error": ""
  },
  "US:WDC": {
    "return_pct": -4.24,
    "value": null,
    "value_type": "return_pct",
    "status": "traded",
    "source": "sina_us_intraday_regular_http",
    "trade_date": "2026-05-19",
    "quote_time_bj": "2026-05-19 22:41:01",
    "fetched_at_bj": "2026-05-19T22:40:56+08:00",
    "error": ""
  },
  "US:MPWR": {
    "return_pct": -3.75,
    "value": null,
    "value_type": "return_pct",
    "status": "traded",
    "source": "sina_us_intraday_regular_http",
    "trade_date": "2026-05-19",
    "quote_time_bj": "2026-05-19 22:41:00",
    "fetched_at_bj": "2026-05-19T22:40:56+08:00",
    "error": ""
  },
  "US:LLY": {
    "return_pct": 1.8,
    "value": null,
    "value_type": "return_pct",
    "status": "traded",
    "source": "sina_us_intraday_regular_http",
    "trade_date": "2026-05-19",
    "quote_time_bj": "2026-05-19 22:41:01",
    "fetched_at_bj": "2026-05-19T22:40:56+08:00",
    "error": ""
  },
  "US:GEV": {
    "return_pct": -1.51,
    "value": null,
    "value_type": "return_pct",
    "status": "traded",
    "source": "sina_us_intraday_regular_http",
    "trade_date": "2026-05-19",
    "quote_time_bj": "2026-05-19 22:41:01",
    "fetched_at_bj": "2026-05-19T22:40:56+08:00",
    "error": ""
  },
  "US:GE": {
    "return_pct": -0.86,
    "value": null,
    "value_type": "return_pct",
    "status": "traded",
    "source": "sina_us_intraday_regular_http",
    "trade_date": "2026-05-19",
    "quote_time_bj": "2026-05-19 22:41:01",
    "fetched_at_bj": "2026-05-19T22:40:56+08:00",
    "error": ""
  },
  "US:ONTO": {
    "return_pct": -5.07,
    "value": null,
    "value_type": "return_pct",
    "status": "traded",
    "source": "sina_us_intraday_regular_http",
    "trade_date": "2026-05-19",
    "quote_time_bj": "2026-05-19 22:41:00",
    "fetched_at_bj": "2026-05-19T22:40:56+08:00",
    "error": ""
  },
  "US:AAOI": {
    "return_pct": -5.2,
    "value": null,
    "value_type": "return_pct",
    "status": "traded",
    "source": "sina_us_intraday_regular_http",
    "trade_date": "2026-05-19",
    "quote_time_bj": "2026-05-19 22:41:01",
    "fetched_at_bj": "2026-05-19T22:40:56+08:00",
    "error": ""
  },
  "HK:00981": {
    "return_pct": -0.29112081513829047,
    "value": null,
    "value_type": "return_pct",
    "status": "traded",
    "source": "ak_stock_hk_daily_sina_qfq_close_calc",
    "trade_date": "2026-05-19",
    "quote_time_bj": "",
    "fetched_at_bj": "2026-05-19T22:40:56+08:00",
    "error": ""
  },
  "HK:01347": {
    "return_pct": 0.6908462867011966,
    "value": null,
    "value_type": "return_pct",
    "status": "traded",
    "source": "ak_stock_hk_daily_sina_qfq_close_calc",
    "trade_date": "2026-05-19",
    "quote_time_bj": "",
    "fetched_at_bj": "2026-05-19T22:40:56+08:00",
    "error": ""
  },
  "US:TXN": {
    "return_pct": -1.49,
    "value": null,
    "value_type": "return_pct",
    "status": "traded",
    "source": "sina_us_intraday_regular_http",
    "trade_date": "2026-05-19",
    "quote_time_bj": "2026-05-19 22:41:01",
    "fetched_at_bj": "2026-05-19T22:40:56+08:00",
    "error": ""
  },
  "US:AMAT": {
    "return_pct": -2.96,
    "value": null,
    "value_type": "return_pct",
    "status": "traded",
    "source": "sina_us_intraday_regular_http",
    "trade_date": "2026-05-19",
    "quote_time_bj": "2026-05-19 22:41:01",
    "fetched_at_bj": "2026-05-19T22:40:56+08:00",
    "error": ""
  },
  "HK:09988": {
    "return_pct": 1.2148823082763993,
    "value": null,
    "value_type": "return_pct",
    "status": "traded",
    "source": "ak_stock_hk_daily_sina_qfq_close_calc",
    "trade_date": "2026-05-19",
    "quote_time_bj": "",
    "fetched_at_bj": "2026-05-19T22:40:56+08:00",
    "error": ""
  },
  "CN:688256": {
    "return_pct": 8.398589963763058,
    "value": null,
    "value_type": "return_pct",
    "status": "traded",
    "source": "ak_stock_zh_a_daily_sina_qfq_close_calc",
    "trade_date": "2026-05-19",
    "quote_time_bj": "",
    "fetched_at_bj": "2026-05-19T22:40:56+08:00",
    "error": ""
  },
  "US:IBB": {
    "return_pct": -0.16,
    "value": null,
    "value_type": "return_pct",
    "status": "traded",
    "source": "sina_us_intraday_regular_http",
    "trade_date": "2026-05-19",
    "quote_time_bj": "2026-05-19 22:41:05",
    "fetched_at_bj": "2026-05-19T22:40:56+08:00",
    "error": ""
  },
  "US:GILD": {
    "return_pct": 0.85,
    "value": null,
    "value_type": "return_pct",
    "status": "traded",
    "source": "sina_us_intraday_regular_http",
    "trade_date": "2026-05-19",
    "quote_time_bj": "2026-05-19 22:41:05",
    "fetched_at_bj": "2026-05-19T22:40:56+08:00",
    "error": ""
  },
  "US:VRTX": {
    "return_pct": 0.9,
    "value": null,
    "value_type": "return_pct",
    "status": "traded",
    "source": "sina_us_intraday_regular_http",
    "trade_date": "2026-05-19",
    "quote_time_bj": "2026-05-19 22:41:04",
    "fetched_at_bj": "2026-05-19T22:40:56+08:00",
    "error": ""
  },
  "US:AMGN": {
    "return_pct": 0.93,
    "value": null,
    "value_type": "return_pct",
    "status": "traded",
    "source": "sina_us_intraday_regular_http",
    "trade_date": "2026-05-19",
    "quote_time_bj": "2026-05-19 22:41:06",
    "fetched_at_bj": "2026-05-19T22:40:56+08:00",
    "error": ""
  },
  "US:REGN": {
    "return_pct": -0.27,
    "value": null,
    "value_type": "return_pct",
    "status": "traded",
    "source": "sina_us_intraday_regular_http",
    "trade_date": "2026-05-19",
    "quote_time_bj": "2026-05-19 22:41:06",
    "fetched_at_bj": "2026-05-19T22:40:56+08:00",
    "error": ""
  },
  "US:ALNY": {
    "return_pct": 2.06,
    "value": null,
    "value_type": "return_pct",
    "status": "traded",
    "source": "sina_us_intraday_regular_http",
    "trade_date": "2026-05-19",
    "quote_time_bj": "2026-05-19 22:41:06",
    "fetched_at_bj": "2026-05-19T22:40:56+08:00",
    "error": ""
  },
  "US:INSM": {
    "return_pct": 0.98,
    "value": null,
    "value_type": "return_pct",
    "status": "traded",
    "source": "sina_us_intraday_regular_http",
    "trade_date": "2026-05-19",
    "quote_time_bj": "2026-05-19 22:41:06",
    "fetched_at_bj": "2026-05-19T22:40:56+08:00",
    "error": ""
  },
  "US:BIIB": {
    "return_pct": -0.79,
    "value": null,
    "value_type": "return_pct",
    "status": "traded",
    "source": "sina_us_intraday_regular_http",
    "trade_date": "2026-05-19",
    "quote_time_bj": "2026-05-19 22:41:03",
    "fetched_at_bj": "2026-05-19T22:40:56+08:00",
    "error": ""
  },
  "US:UTHR": {
    "return_pct": 0.58,
    "value": null,
    "value_type": "return_pct",
    "status": "traded",
    "source": "sina_us_intraday_regular_http",
    "trade_date": "2026-05-19",
    "quote_time_bj": "2026-05-19 22:41:05",
    "fetched_at_bj": "2026-05-19T22:40:56+08:00",
    "error": ""
  },
  "US:ARGX": {
    "return_pct": 1.39,
    "value": null,
    "value_type": "return_pct",
    "status": "traded",
    "source": "sina_us_intraday_regular_http",
    "trade_date": "2026-05-19",
    "quote_time_bj": "2026-05-19 22:41:04",
    "fetched_at_bj": "2026-05-19T22:40:56+08:00",
    "error": ""
  },
  "US:RPRX": {
    "return_pct": -0.08,
    "value": null,
    "value_type": "return_pct",
    "status": "traded",
    "source": "sina_us_intraday_regular_http",
    "trade_date": "2026-05-19",
    "quote_time_bj": "2026-05-19 22:41:05",
    "fetched_at_bj": "2026-05-19T22:40:56+08:00",
    "error": ""
  },
  "HK:01088": {
    "return_pct": -0.3561887800534347,
    "value": null,
    "value_type": "return_pct",
    "status": "traded",
    "source": "ak_stock_hk_daily_sina_qfq_close_calc",
    "trade_date": "2026-05-19",
    "quote_time_bj": "",
    "fetched_at_bj": "2026-05-19T22:40:56+08:00",
    "error": ""
  },
  "HK:00883": {
    "return_pct": 2.9895366218235964,
    "value": null,
    "value_type": "return_pct",
    "status": "traded",
    "source": "ak_stock_hk_daily_sina_qfq_close_calc",
    "trade_date": "2026-05-19",
    "quote_time_bj": "",
    "fetched_at_bj": "2026-05-19T22:40:56+08:00",
    "error": ""
  },
  "US:SPY": {
    "return_pct": -0.73,
    "value": null,
    "value_type": "return_pct",
    "status": "traded",
    "source": "sina_us_intraday_regular_http",
    "trade_date": "2026-05-19",
    "quote_time_bj": "2026-05-19 22:41:11",
    "fetched_at_bj": "2026-05-19T22:40:56+08:00",
    "error": ""
  },
  "US:COP": {
    "return_pct": 0.4,
    "value": null,
    "value_type": "return_pct",
    "status": "traded",
    "source": "sina_us_intraday_regular_http",
    "trade_date": "2026-05-19",
    "quote_time_bj": "2026-05-19 22:41:11",
    "fetched_at_bj": "2026-05-19T22:40:56+08:00",
    "error": ""
  },
  "US:XOM": {
    "return_pct": 0.55,
    "value": null,
    "value_type": "return_pct",
    "status": "traded",
    "source": "sina_us_intraday_regular_http",
    "trade_date": "2026-05-19",
    "quote_time_bj": "2026-05-19 22:41:11",
    "fetched_at_bj": "2026-05-19T22:40:56+08:00",
    "error": ""
  },
  "US:CVX": {
    "return_pct": 0.28,
    "value": null,
    "value_type": "return_pct",
    "status": "traded",
    "source": "sina_us_intraday_regular_http",
    "trade_date": "2026-05-19",
    "quote_time_bj": "2026-05-19 22:41:11",
    "fetched_at_bj": "2026-05-19T22:40:56+08:00",
    "error": ""
  },
  "US:T": {
    "return_pct": 1.6,
    "value": null,
    "value_type": "return_pct",
    "status": "traded",
    "source": "sina_us_intraday_regular_http",
    "trade_date": "2026-05-19",
    "quote_time_bj": "2026-05-19 22:41:11",
    "fetched_at_bj": "2026-05-19T22:40:56+08:00",
    "error": ""
  },
  "US:MDLZ": {
    "return_pct": 1.18,
    "value": null,
    "value_type": "return_pct",
    "status": "traded",
    "source": "sina_us_intraday_regular_http",
    "trade_date": "2026-05-19",
    "quote_time_bj": "2026-05-19 22:41:11",
    "fetched_at_bj": "2026-05-19T22:40:56+08:00",
    "error": ""
  },
  "US:C": {
    "return_pct": -1.0,
    "value": null,
    "value_type": "return_pct",
    "status": "traded",
    "source": "sina_us_intraday_regular_http",
    "trade_date": "2026-05-19",
    "quote_time_bj": "2026-05-19 22:41:11",
    "fetched_at_bj": "2026-05-19T22:40:56+08:00",
    "error": ""
  },
  "US:WFC": {
    "return_pct": 1.16,
    "value": null,
    "value_type": "return_pct",
    "status": "traded",
    "source": "sina_us_intraday_regular_http",
    "trade_date": "2026-05-19",
    "quote_time_bj": "2026-05-19 22:41:11",
    "fetched_at_bj": "2026-05-19T22:40:56+08:00",
    "error": ""
  },
  "US:MRK": {
    "return_pct": 1.19,
    "value": null,
    "value_type": "return_pct",
    "status": "traded",
    "source": "sina_us_intraday_regular_http",
    "trade_date": "2026-05-19",
    "quote_time_bj": "2026-05-19 22:41:10",
    "fetched_at_bj": "2026-05-19T22:40:56+08:00",
    "error": ""
  },
  "US:CRCL": {
    "return_pct": -0.57,
    "value": null,
    "value_type": "return_pct",
    "status": "traded",
    "source": "sina_us_intraday_regular_http",
    "trade_date": "2026-05-19",
    "quote_time_bj": "2026-05-19 22:41:11",
    "fetched_at_bj": "2026-05-19T22:40:56+08:00",
    "error": ""
  },
  "US:BTI": {
    "return_pct": -1.22,
    "value": null,
    "value_type": "return_pct",
    "status": "traded",
    "source": "sina_us_intraday_regular_http",
    "trade_date": "2026-05-19",
    "quote_time_bj": "2026-05-19 22:41:11",
    "fetched_at_bj": "2026-05-19T22:40:56+08:00",
    "error": ""
  },
  "US:JBL": {
    "return_pct": -3.75,
    "value": null,
    "value_type": "return_pct",
    "status": "traded",
    "source": "sina_us_intraday_regular_http",
    "trade_date": "2026-05-19",
    "quote_time_bj": "2026-05-19 22:41:10",
    "fetched_at_bj": "2026-05-19T22:40:56+08:00",
    "error": ""
  },
  "US:APA": {
    "return_pct": 0.27,
    "value": null,
    "value_type": "return_pct",
    "status": "traded",
    "source": "sina_us_intraday_regular_http",
    "trade_date": "2026-05-19",
    "quote_time_bj": "2026-05-19 22:41:16",
    "fetched_at_bj": "2026-05-19T22:40:56+08:00",
    "error": ""
  },
  "US:DOW": {
    "return_pct": -2.31,
    "value": null,
    "value_type": "return_pct",
    "status": "traded",
    "source": "sina_us_intraday_regular_http",
    "trade_date": "2026-05-19",
    "quote_time_bj": "2026-05-19 22:41:16",
    "fetched_at_bj": "2026-05-19T22:40:56+08:00",
    "error": ""
  },
  "US:LYB": {
    "return_pct": -1.73,
    "value": null,
    "value_type": "return_pct",
    "status": "traded",
    "source": "sina_us_intraday_regular_http",
    "trade_date": "2026-05-19",
    "quote_time_bj": "2026-05-19 22:41:16",
    "fetched_at_bj": "2026-05-19T22:40:56+08:00",
    "error": ""
  },
  "US:OXY": {
    "return_pct": 0.72,
    "value": null,
    "value_type": "return_pct",
    "status": "traded",
    "source": "sina_us_intraday_regular_http",
    "trade_date": "2026-05-19",
    "quote_time_bj": "2026-05-19 22:41:16",
    "fetched_at_bj": "2026-05-19T22:40:56+08:00",
    "error": ""
  },
  "US:DELL": {
    "return_pct": -2.83,
    "value": null,
    "value_type": "return_pct",
    "status": "traded",
    "source": "sina_us_intraday_regular_http",
    "trade_date": "2026-05-19",
    "quote_time_bj": "2026-05-19 22:41:16",
    "fetched_at_bj": "2026-05-19T22:40:56+08:00",
    "error": ""
  },
  "US:DAL": {
    "return_pct": -2.38,
    "value": null,
    "value_type": "return_pct",
    "status": "traded",
    "source": "sina_us_intraday_regular_http",
    "trade_date": "2026-05-19",
    "quote_time_bj": "2026-05-19 22:41:16",
    "fetched_at_bj": "2026-05-19T22:40:56+08:00",
    "error": ""
  },
  "US:FANG": {
    "return_pct": 0.65,
    "value": null,
    "value_type": "return_pct",
    "status": "traded",
    "source": "sina_us_intraday_regular_http",
    "trade_date": "2026-05-19",
    "quote_time_bj": "2026-05-19 22:41:13",
    "fetched_at_bj": "2026-05-19T22:40:56+08:00",
    "error": ""
  },
  "US:EOG": {
    "return_pct": 0.58,
    "value": null,
    "value_type": "return_pct",
    "status": "traded",
    "source": "sina_us_intraday_regular_http",
    "trade_date": "2026-05-19",
    "quote_time_bj": "2026-05-19 22:41:15",
    "fetched_at_bj": "2026-05-19T22:40:56+08:00",
    "error": ""
  },
  "US:XOP": {
    "return_pct": 0.12,
    "value": null,
    "value_type": "return_pct",
    "status": "traded",
    "source": "sina_us_intraday_regular_http",
    "trade_date": "2026-05-19",
    "quote_time_bj": "2026-05-19 22:41:16",
    "fetched_at_bj": "2026-05-19T22:40:56+08:00",
    "error": ""
  },
  "US:VG": {
    "return_pct": 0.32,
    "value": null,
    "value_type": "return_pct",
    "status": "traded",
    "source": "sina_us_intraday_regular_http",
    "trade_date": "2026-05-19",
    "quote_time_bj": "2026-05-19 22:41:16",
    "fetched_at_bj": "2026-05-19T22:40:56+08:00",
    "error": ""
  },
  "US:SM": {
    "return_pct": 1.3,
    "value": null,
    "value_type": "return_pct",
    "status": "traded",
    "source": "sina_us_intraday_regular_http",
    "trade_date": "2026-05-19",
    "quote_time_bj": "2026-05-19 22:41:16",
    "fetched_at_bj": "2026-05-19T22:40:56+08:00",
    "error": ""
  },
  "US:MUR": {
    "return_pct": -0.49,
    "value": null,
    "value_type": "return_pct",
    "status": "traded",
    "source": "sina_us_intraday_regular_http",
    "trade_date": "2026-05-19",
    "quote_time_bj": "2026-05-19 22:41:16",
    "fetched_at_bj": "2026-05-19T22:40:56+08:00",
    "error": ""
  },
  "US:CHRD": {
    "return_pct": -0.04,
    "value": null,
    "value_type": "return_pct",
    "status": "traded",
    "source": "sina_us_intraday_regular_http",
    "trade_date": "2026-05-19",
    "quote_time_bj": "2026-05-19 22:41:14",
    "fetched_at_bj": "2026-05-19T22:40:56+08:00",
    "error": ""
  },
  "US:PBF": {
    "return_pct": -1.57,
    "value": null,
    "value_type": "return_pct",
    "status": "traded",
    "source": "sina_us_intraday_regular_http",
    "trade_date": "2026-05-19",
    "quote_time_bj": "2026-05-19 22:41:15",
    "fetched_at_bj": "2026-05-19T22:40:56+08:00",
    "error": ""
  },
  "US:MTDR": {
    "return_pct": 0.38,
    "value": null,
    "value_type": "return_pct",
    "status": "traded",
    "source": "sina_us_intraday_regular_http",
    "trade_date": "2026-05-19",
    "quote_time_bj": "2026-05-19 22:41:15",
    "fetched_at_bj": "2026-05-19T22:40:56+08:00",
    "error": ""
  },
  "US:PSX": {
    "return_pct": 0.42,
    "value": null,
    "value_type": "return_pct",
    "status": "traded",
    "source": "sina_us_intraday_regular_http",
    "trade_date": "2026-05-19",
    "quote_time_bj": "2026-05-19 22:41:28",
    "fetched_at_bj": "2026-05-19T22:40:56+08:00",
    "error": ""
  },
  "US:MPC": {
    "return_pct": -0.43,
    "value": null,
    "value_type": "return_pct",
    "status": "traded",
    "source": "sina_us_intraday_regular_http",
    "trade_date": "2026-05-19",
    "quote_time_bj": "2026-05-19 22:41:31",
    "fetched_at_bj": "2026-05-19T22:40:56+08:00",
    "error": ""
  },
  "US:VLO": {
    "return_pct": 0.33,
    "value": null,
    "value_type": "return_pct",
    "status": "traded",
    "source": "sina_us_intraday_regular_http",
    "trade_date": "2026-05-19",
    "quote_time_bj": "2026-05-19 22:41:30",
    "fetched_at_bj": "2026-05-19T22:40:56+08:00",
    "error": ""
  },
  "US:DVN": {
    "return_pct": -0.48,
    "value": null,
    "value_type": "return_pct",
    "status": "traded",
    "source": "sina_us_intraday_regular_http",
    "trade_date": "2026-05-19",
    "quote_time_bj": "2026-05-19 22:41:31",
    "fetched_at_bj": "2026-05-19T22:40:56+08:00",
    "error": ""
  },
  "US:TPL": {
    "return_pct": -0.34,
    "value": null,
    "value_type": "return_pct",
    "status": "traded",
    "source": "sina_us_intraday_regular_http",
    "trade_date": "2026-05-19",
    "quote_time_bj": "2026-05-19 22:41:28",
    "fetched_at_bj": "2026-05-19T22:40:56+08:00",
    "error": ""
  },
  "US:EQT": {
    "return_pct": 1.85,
    "value": null,
    "value_type": "return_pct",
    "status": "traded",
    "source": "sina_us_intraday_regular_http",
    "trade_date": "2026-05-19",
    "quote_time_bj": "2026-05-19 22:41:31",
    "fetched_at_bj": "2026-05-19T22:40:56+08:00",
    "error": ""
  },
  "HK:01179": {
    "return_pct": 1.2841987716359693,
    "value": null,
    "value_type": "return_pct",
    "status": "traded",
    "source": "ak_stock_hk_daily_sina_qfq_close_calc",
    "trade_date": "2026-05-19",
    "quote_time_bj": "",
    "fetched_at_bj": "2026-05-19T22:40:56+08:00",
    "error": ""
  },
  "HK:00700": {
    "return_pct": 2.404274265360651,
    "value": null,
    "value_type": "return_pct",
    "status": "traded",
    "source": "ak_stock_hk_daily_sina_qfq_close_calc",
    "trade_date": "2026-05-19",
    "quote_time_bj": "",
    "fetched_at_bj": "2026-05-19T22:40:56+08:00",
    "error": ""
  },
  "US:FUTU": {
    "return_pct": -3.41,
    "value": null,
    "value_type": "return_pct",
    "status": "traded",
    "source": "sina_us_intraday_regular_http",
    "trade_date": "2026-05-19",
    "quote_time_bj": "2026-05-19 22:41:35",
    "fetched_at_bj": "2026-05-19T22:40:56+08:00",
    "error": ""
  },
  "HK:00100": {
    "return_pct": -7.187500000000002,
    "value": null,
    "value_type": "return_pct",
    "status": "traded",
    "source": "ak_stock_hk_daily_sina_qfq_close_calc",
    "trade_date": "2026-05-19",
    "quote_time_bj": "",
    "fetched_at_bj": "2026-05-19T22:40:56+08:00",
    "error": ""
  },
  "HK:06869": {
    "return_pct": -2.4106400665004135,
    "value": null,
    "value_type": "return_pct",
    "status": "traded",
    "source": "ak_stock_hk_daily_sina_qfq_close_calc",
    "trade_date": "2026-05-19",
    "quote_time_bj": "",
    "fetched_at_bj": "2026-05-19T22:40:56+08:00",
    "error": ""
  },
  "CN:688519": {
    "return_pct": 1.9510854630393037,
    "value": null,
    "value_type": "return_pct",
    "status": "traded",
    "source": "ak_stock_zh_a_daily_sina_qfq_close_calc",
    "trade_date": "2026-05-19",
    "quote_time_bj": "",
    "fetched_at_bj": "2026-05-19T22:40:56+08:00",
    "error": ""
  },
  "US:CAT": {
    "return_pct": -1.14,
    "value": null,
    "value_type": "return_pct",
    "status": "traded",
    "source": "sina_us_intraday_regular_http",
    "trade_date": "2026-05-19",
    "quote_time_bj": "2026-05-19 22:41:36",
    "fetched_at_bj": "2026-05-19T22:40:56+08:00",
    "error": ""
  },
  "US:NIO": {
    "return_pct": -2.22,
    "value": null,
    "value_type": "return_pct",
    "status": "traded",
    "source": "sina_us_intraday_regular_http",
    "trade_date": "2026-05-19",
    "quote_time_bj": "2026-05-19 22:41:36",
    "fetched_at_bj": "2026-05-19T22:40:56+08:00",
    "error": ""
  },
  "US:CVNA": {
    "return_pct": -2.54,
    "value": null,
    "value_type": "return_pct",
    "status": "traded",
    "source": "sina_us_intraday_regular_http",
    "trade_date": "2026-05-19",
    "quote_time_bj": "2026-05-19 22:41:36",
    "fetched_at_bj": "2026-05-19T22:40:56+08:00",
    "error": ""
  },
  "US:RIVN": {
    "return_pct": -3.82,
    "value": null,
    "value_type": "return_pct",
    "status": "traded",
    "source": "sina_us_intraday_regular_http",
    "trade_date": "2026-05-19",
    "quote_time_bj": "2026-05-19 22:41:36",
    "fetched_at_bj": "2026-05-19T22:40:56+08:00",
    "error": ""
  },
  "US:RACE": {
    "return_pct": 2.93,
    "value": null,
    "value_type": "return_pct",
    "status": "traded",
    "source": "sina_us_intraday_regular_http",
    "trade_date": "2026-05-19",
    "quote_time_bj": "2026-05-19 22:41:36",
    "fetched_at_bj": "2026-05-19T22:40:56+08:00",
    "error": ""
  },
  "US:PONY": {
    "return_pct": -0.73,
    "value": null,
    "value_type": "return_pct",
    "status": "traded",
    "source": "sina_us_intraday_regular_http",
    "trade_date": "2026-05-19",
    "quote_time_bj": "2026-05-19 22:41:35",
    "fetched_at_bj": "2026-05-19T22:40:56+08:00",
    "error": ""
  },
  "HK:03750": {
    "return_pct": -2.1497405485544796,
    "value": null,
    "value_type": "return_pct",
    "status": "traded",
    "source": "ak_stock_hk_daily_sina_qfq_close_calc",
    "trade_date": "2026-05-19",
    "quote_time_bj": "",
    "fetched_at_bj": "2026-05-19T22:40:56+08:00",
    "error": ""
  },
  "US:HD": {
    "return_pct": 0.68,
    "value": null,
    "value_type": "return_pct",
    "status": "traded",
    "source": "sina_us_intraday_regular_http",
    "trade_date": "2026-05-19",
    "quote_time_bj": "2026-05-19 22:41:36",
    "fetched_at_bj": "2026-05-19T22:40:56+08:00",
    "error": ""
  },
  "US:MCD": {
    "return_pct": 0.64,
    "value": null,
    "value_type": "return_pct",
    "status": "traded",
    "source": "sina_us_intraday_regular_http",
    "trade_date": "2026-05-19",
    "quote_time_bj": "2026-05-19 22:41:36",
    "fetched_at_bj": "2026-05-19T22:40:56+08:00",
    "error": ""
  },
  "US:TJX": {
    "return_pct": 0.68,
    "value": null,
    "value_type": "return_pct",
    "status": "traded",
    "source": "sina_us_intraday_regular_http",
    "trade_date": "2026-05-19",
    "quote_time_bj": "2026-05-19 22:41:41",
    "fetched_at_bj": "2026-05-19T22:40:56+08:00",
    "error": ""
  },
  "US:BKNG": {
    "return_pct": 2.7,
    "value": null,
    "value_type": "return_pct",
    "status": "traded",
    "source": "sina_us_intraday_regular_http",
    "trade_date": "2026-05-19",
    "quote_time_bj": "2026-05-19 22:41:41",
    "fetched_at_bj": "2026-05-19T22:40:56+08:00",
    "error": ""
  },
  "US:LOW": {
    "return_pct": 0.56,
    "value": null,
    "value_type": "return_pct",
    "status": "traded",
    "source": "sina_us_intraday_regular_http",
    "trade_date": "2026-05-19",
    "quote_time_bj": "2026-05-19 22:41:41",
    "fetched_at_bj": "2026-05-19T22:40:56+08:00",
    "error": ""
  },
  "US:SBUX": {
    "return_pct": 0.2,
    "value": null,
    "value_type": "return_pct",
    "status": "traded",
    "source": "sina_us_intraday_regular_http",
    "trade_date": "2026-05-19",
    "quote_time_bj": "2026-05-19 22:41:37",
    "fetched_at_bj": "2026-05-19T22:40:56+08:00",
    "error": ""
  },
  "US:ORLY": {
    "return_pct": 0.46,
    "value": null,
    "value_type": "return_pct",
    "status": "traded",
    "source": "sina_us_intraday_regular_http",
    "trade_date": "2026-05-19",
    "quote_time_bj": "2026-05-19 22:41:41",
    "fetched_at_bj": "2026-05-19T22:40:56+08:00",
    "error": ""
  },
  "US:MAR": {
    "return_pct": -0.04,
    "value": null,
    "value_type": "return_pct",
    "status": "traded",
    "source": "sina_us_intraday_regular_http",
    "trade_date": "2026-05-19",
    "quote_time_bj": "2026-05-19 22:41:38",
    "fetched_at_bj": "2026-05-19T22:40:56+08:00",
    "error": ""
  },
  "US:PLTR": {
    "return_pct": -0.06,
    "value": null,
    "value_type": "return_pct",
    "status": "traded",
    "source": "sina_us_intraday_regular_http",
    "trade_date": "2026-05-19",
    "quote_time_bj": "2026-05-19 22:41:41",
    "fetched_at_bj": "2026-05-19T22:40:56+08:00",
    "error": ""
  },
  "US:CSCO": {
    "return_pct": -2.92,
    "value": null,
    "value_type": "return_pct",
    "status": "traded",
    "source": "sina_us_intraday_regular_http",
    "trade_date": "2026-05-19",
    "quote_time_bj": "2026-05-19 22:41:41",
    "fetched_at_bj": "2026-05-19T22:40:56+08:00",
    "error": ""
  },
  "US:SMH": {
    "return_pct": -2.35,
    "value": null,
    "value_type": "return_pct",
    "status": "traded",
    "source": "sina_us_intraday_regular_http",
    "trade_date": "2026-05-19",
    "quote_time_bj": "2026-05-19 22:41:41",
    "fetched_at_bj": "2026-05-19T22:40:56+08:00",
    "error": ""
  },
  "US:GLD": {
    "return_pct": -1.5,
    "value": null,
    "value_type": "return_pct",
    "status": "traded",
    "source": "sina_us_intraday_regular_http",
    "trade_date": "2026-05-19",
    "quote_time_bj": "2026-05-19 22:41:41",
    "fetched_at_bj": "2026-05-19T22:40:56+08:00",
    "error": ""
  },
  "VIX_LEVEL:VIX": {
    "return_pct": null,
    "value": 17.82,
    "value_type": "level",
    "status": "traded",
    "source": "vix_latest_close_fallback:CBOE",
    "trade_date": "2026-05-18",
    "quote_time_bj": "",
    "fetched_at_bj": "2026-05-19T22:40:56+08:00",
    "error": "VIX 实时点位获取失败: https://query1.finance.yahoo.com/v8/finance/chart/%5EVIX: HTTPError('403 Client Error: Forbidden for url: https://query1.finance.yahoo.com/v8/finance/chart/%5EVIX?range=1d&interval=1m&includePrePost=true') | https://query2.finance.yahoo.com/v8/finance/chart/%5EVIX: HTTPError('403 Client Error: Forbidden for url: https://query2.finance.yahoo.com/v8/finance/chart/%5EVIX?range=1d&interval=1m&includePrePost=true')"
  }
}
